ckanext/__init__.py
ckanext/doi/__init__.py
ckanext/doi/cli.py
ckanext/doi/interfaces.py
ckanext/doi/plugin.py
ckanext/doi/lib/__init__.py
ckanext/doi/lib/api.py
ckanext/doi/lib/errors.py
ckanext/doi/lib/helpers.py
ckanext/doi/lib/metadata.py
ckanext/doi/lib/xml_utils.py
ckanext/doi/migration/doi/README
ckanext/doi/migration/doi/alembic.ini
ckanext/doi/migration/doi/env.py
ckanext/doi/migration/doi/script.py.mako
ckanext/doi/migration/doi/versions/86a245a136db_initialisation.py
ckanext/doi/model/__init__.py
ckanext/doi/model/crud.py
ckanext/doi/model/doi.py
ckanext/doi/theme/templates/doi/snippets/package_citation.html
ckanext/doi/theme/templates/doi/snippets/resource_citation.html
ckanext/doi/theme/templates/package/read.html
ckanext/doi/theme/templates/package/read_base.html
ckanext/doi/theme/templates/package/resource_read.html
ckanext/doi/theme/templates/package/snippets/package_basic_fields.html
ckanext/doi/theme/templates/package/snippets/package_metadata_fields.html
ckanext_doi-4.0.4.dist-info/licenses/LICENSE
docs/_scripts/gen_api_pages.py
tests/helpers/__init__.py
tests/helpers/constants.py
ckanext_doi-4.0.4.dist-info/METADATA
ckanext_doi-4.0.4.dist-info/WHEEL
ckanext_doi-4.0.4.dist-info/entry_points.txt
ckanext_doi-4.0.4.dist-info/top_level.txt
ckanext_doi-4.0.4.dist-info/RECORD
