Metadata-Version: 2.4
Name: ckanext-doi
Version: 4.0.4
Summary: A CKAN extension for assigning a digital object identifier (DOI) to datasets, using the DataCite DOI service.
Author-email: Natural History Museum <data@nhm.ac.uk>
License: GPL-3.0-or-later
Project-URL: repository, https://github.com/NaturalHistoryMuseum/ckanext-doi
Project-URL: changelog, https://github.com/NaturalHistoryMuseum/ckanext-doi/blob/main/CHANGELOG.md
Keywords: CKAN,data,doi
Classifier: Development Status :: 5 - Production/Stable
Classifier: License :: OSI Approved :: GNU General Public License v3 (GPLv3)
Classifier: Programming Language :: Python
Classifier: Programming Language :: Python :: 3 :: Only
Classifier: Programming Language :: Python :: 3.6
Classifier: Programming Language :: Python :: 3.7
Classifier: Programming Language :: Python :: 3.8
Requires-Python: >=3.6
License-File: LICENSE
Requires-Dist: jsonschema==3.0.0
Requires-Dist: xmltodict==0.12.0
Requires-Dist: datacite==1.1.2
Requires-Dist: ckantools>=0.4.2
Provides-Extra: test
Requires-Dist: mock; extra == "test"
Requires-Dist: pytest>=4.6.5; extra == "test"
Requires-Dist: pytest-cov>=2.7.1; extra == "test"
Requires-Dist: coveralls; extra == "test"
Dynamic: license-file
